future_shot/__init__.py
future_shot/data.py
future_shot/few_shot.py
future_shot/lightning.py
future_shot/model.py
future_shot/module.py
future_shot/trainer.py
future_shot/extra/__init__.py
future_shot/extra/wandb.py
future_shot/extra/timm/__init__.py
future_shot/extra/timm/model.py
future_shot/extra/timm/preprocessing.py
future_shot/extra/transformer/__init__.py
future_shot/extra/transformer/lr_scheduler.py
future_shot/extra/transformer/preprocessing.py
future_shot-0.0.1.dist-info/LICENSE
future_shot-0.0.1.dist-info/METADATA
future_shot-0.0.1.dist-info/WHEEL
future_shot-0.0.1.dist-info/top_level.txt
future_shot-0.0.1.dist-info/RECORD
