Metadata-Version: 2.1
Name: future-shot
Version: 0.0.1
Summary: FutureShot: Few-Shot Learning for high-dimensional classification problems
Author-email: "Fernando H. F. Camargo" <fernando.camargo.ai@gmail.com>
Maintainer-email: "Fernando H. F. Camargo" <fernando.camargo.ai@gmail.com>
License: Apache License
Project-URL: homepage, https://github.com/fernandocamargoai/future-shot
Project-URL: repository, https://github.com/fernandocamargoai/future-shot
Project-URL: documentation, https://github.com/fernandocamargoai/future-shot/blob/main/README.md
Keywords: machine learning,fewshot learning
Classifier: Development Status :: 3 - Alpha
Classifier: Intended Audience :: Developers
Classifier: Intended Audience :: Education
Classifier: Intended Audience :: Science/Research
Classifier: License :: OSI Approved :: Apache Software License
Classifier: Operating System :: OS Independent
Classifier: Programming Language :: Python :: 3
Classifier: Programming Language :: Python :: 3.9
Classifier: Programming Language :: Python :: 3.10
Classifier: Programming Language :: Python :: 3.11
Classifier: Programming Language :: Python :: 3.12
Classifier: Programming Language :: Python :: 3 :: Only
Classifier: Topic :: Scientific/Engineering :: Artificial Intelligence
Requires-Python: >=3.9
License-File: LICENSE
Requires-Dist: torch >=1.11.0
Requires-Dist: pytorch-lightning >=2.0.0
Requires-Dist: jsonargparse[signatures]
Requires-Dist: datasets >=2.3.0
Requires-Dist: evaluate >=0.3.0
Requires-Dist: scikit-learn >=1.0.0
Provides-Extra: timm
Requires-Dist: timm >=0.9 ; extra == 'timm'
Provides-Extra: transformers
Requires-Dist: sentence-transformers >=2.2.2 ; extra == 'transformers'
Provides-Extra: wandb
Requires-Dist: wandb ; extra == 'wandb'
